<?xml version="1.0" encoding="utf-8"?>
<diff xmlns:xsi="http://www.w3.org/2001/XMLSchema-instance">
	<!-- STATIONS STATIONS STATIONS STATIONS STATIONS STATIONS -->
	<add sel="//god/stations">
		<station id="dga_defence_cluster_DGA1_sector001" race="argon" owner="galdente" type="factory">
			<quotas>
				<quota galaxy="1" zone="1"/>
			</quotas>
			<location class="zone" macro="ZoneDGA2_Cluster_DGA1_Sector001_macro" matchextension="false"/>
			<station>
				<select faction="galdente" tags="[defence]"/>
			</station>
		</station>
		<station id="dga_defence_cluster_DGA1_sector001_02" race="argon" owner="galdente" type="factory">
			<quotas>
				<quota galaxy="1" zone="1"/>
			</quotas>
			<location class="zone" macro="ZoneDGA6_Cluster_DGA1_Sector001_macro" matchextension="false"/>
			<station>
				<select faction="galdente" tags="[defence]"/>
			</station>
		</station>
		<station id="dga_defence_cluster_DGA2_sector001" race="argon" owner="galdente" type="factory">
			<quotas>
				<quota galaxy="1" zone="1"/>
			</quotas>
			<location class="zone" macro="ZoneDGAc_Cluster_DGA2_Sector001_macro" matchextension="false"/>
			<station>
				<select faction="galdente" tags="[defence]"/>
			</station>
		</station>
		<station id="dga_defence_cluster_DGA2_sector001_02" race="argon" owner="galdente" type="factory">
			<quotas>
				<quota galaxy="1" zone="1"/>
			</quotas>
			<location class="zone" macro="ZoneDGA6_Cluster_DGA2_Sector001_macro" matchextension="false"/>
			<station>
				<select faction="galdente" tags="[defence]"/>
			</station>
		</station>
		<station id="dga_defence_cluster_DGA3_sector001" race="argon" owner="galdente" type="factory">
			<quotas>
				<quota galaxy="1" zone="1"/>
			</quotas>
			<location class="zone" macro="ZoneDGAc_Cluster_DGA3_Sector001_macro" matchextension="false"/>
			<station>
				<select faction="galdente" tags="[defence]"/>
			</station>
		</station>
		<station id="dga_defence_cluster_DGA3_sector001_02" race="argon" owner="galdente" type="factory">
			<quotas>
				<quota galaxy="1" zone="1"/>
			</quotas>
			<location class="zone" macro="ZoneDGA2_Cluster_DGA3_Sector001_macro" matchextension="false"/>
			<station>
				<select faction="galdente" tags="[defence]"/>
			</station>
		</station>
		<station id="dga_defence_cluster_DGA4_sector001" race="argon" owner="galdente" type="factory">
			<quotas>
				<quota galaxy="1" zone="1"/>
			</quotas>
			<location class="zone" macro="ZoneDGAc_Cluster_DGA4_Sector001_macro" matchextension="false"/>
			<station>
				<select faction="galdente" tags="[defence]"/>
			</station>
		</station>
		<station id="dga_defence_cluster_DGA5_sector001" race="argon" owner="galdente" type="factory">
			<quotas>
				<quota galaxy="1" zone="1"/>
			</quotas>
			<location class="zone" macro="ZoneDGAc_Cluster_DGA5_Sector001_macro" matchextension="false"/>
			<station>
				<select faction="galdente" tags="[defence]"/>
			</station>
		</station>
		<station id="dga_defence_cluster_DGA6_sector001" race="argon" owner="galdente" type="factory">
			<quotas>
				<quota galaxy="1" zone="1"/>
			</quotas>
			<location class="zone" macro="ZoneDGAc_Cluster_DGA6_Sector001_macro" matchextension="false"/>
			<station>
				<select faction="galdente" tags="[defence]"/>
			</station>
		</station>
		<station id="dga_defence_cluster_DGA7_sector001" race="argon" owner="galdente" type="factory">
			<quotas>
				<quota galaxy="1" zone="1"/>
			</quotas>
			<location class="zone" macro="ZoneDGAc_Cluster_DGA7_Sector001_macro" matchextension="false"/>
			<station>
				<select faction="galdente" tags="[defence]"/>
			</station>
		</station>
		<station id="shipyard_galdente_01" race="argon" owner="galdente" type="factory">
			<quotas>
				<quota galaxy="1" zone="1"/>
			</quotas>
			<location class="zone" macro="ZoneDGAcw_Cluster_DGA4_Sector001_macro" matchextension="false"/>
			<position x="-20000" y="0" z="-20000" pitch="0" yaw="0" roll="0"/>
			<station>
				<select faction="galdente" tags="[shipyard]"/>
				<loadout>
					<level exact="1.0"/>
				</loadout>
			</station>
		</station>
		<station id="wharf_galdente_01" race="argon" owner="galdente" type="factory">
			<quotas>
				<quota galaxy="1" zone="1"/>
			</quotas>
			<location class="zone" macro="ZoneDGAce_Cluster_DGA4_Sector001_macro" matchextension="false"/>
			<position x="20000" y="0" z="-20000" pitch="0" yaw="0" roll="0"/>
			<station>
				<select faction="galdente" tags="[wharf]"/>
				<loadout>
					<level exact="1.0"/>
				</loadout>
			</station>
		</station>
		<station id="tradestation_galdente_01" race="argon" owner="galdente" type="tradingstation">
			<quotas>
				<quota galaxy="1" zone="1"/>
			</quotas>
			<location class="zone" macro="ZoneDGAc_Cluster_DGA1_Sector001_macro" matchextension="false"/>
			<station>
				<select faction="galdente" tags="[tradestation]"/>
				<loadout>
					<level min="0.75" max="1.0"/>
				</loadout>
			</station>
		</station>
		<station id="equipmentdock_galdente_01" race="argon" owner="galdente" type="factory">
			<quotas>
				<quota galaxy="1" zone="1"/>
			</quotas>
			<location class="zone" macro="ZoneDGAc_Cluster_DGA1_Sector001_macro" matchextension="false"/>
			<station>
				<select faction="galdente" tags="[equipmentdock]"/>
				<loadout>
					<level exact="1.0"/>
				</loadout>
			</station>
		</station>
	</add>
	<!-- END STATIONS END STATIONS END STATIONS END STATIONS END STATIONS END STATIONS END STATIONS END STATIONS -->
	<!-- PRODUCTS PRODUCTS PRODUCTS PRODUCTS PRODUCTS PRODUCTS PRODUCTS PRODUCTS -->
	<add sel="//god/products">
		<product id="dga_advancedcomposites" ware="advancedcomposites" owner="galdente" type="factory">
			<quotas>
				<quota galaxy="2"/>
			</quotas>
			<location class="galaxy" macro="xu_ep2_universe_macro" faction="[galdente]" relation="self" comparison="exact" matchextension="false">
				<security min="0.6" max="0.8"/>
			</location>
			<module>
				<select ware="advancedcomposites" race="argon" faction="galdente"/>
			</module>
		</product>
		<product id="dga_advancedelectronics" ware="advancedelectronics" owner="galdente" type="factory">
			<quotas>
				<quota galaxy="2"/>
			</quotas>
			<location class="galaxy" macro="xu_ep2_universe_macro" faction="[galdente]" relation="self" comparison="exact" matchextension="false" newzonechance="0">
				<security min="0.8"/>
			</location>
			<module>
				<select ware="advancedelectronics" race="argon" faction="galdente"/>
			</module>
		</product>
		<product id="dga_antimattercells" ware="antimattercells" owner="galdente" type="factory">
			<quotas>
				<quota galaxy="3"/>
			</quotas>
			<location class="galaxy" macro="xu_ep2_universe_macro" faction="[galdente]" relation="self" comparison="exact" matchextension="false">
				<region ware="hydrogen" max="100000"/>
			</location>
			<module>
				<select ware="antimattercells" race="argon" faction="galdente"/>
			</module>
		</product>
		<product id="dga_antimatterconverters" ware="antimatterconverters" owner="galdente" type="factory">
			<quotas>
				<quota galaxy="2"/>
			</quotas>
			<location class="galaxy" macro="xu_ep2_universe_macro" faction="[galdente]" relation="self" comparison="exact" matchextension="false">
				<security min="0.6" max="0.8"/>
			</location>
			<module>
				<select ware="antimatterconverters" race="argon" faction="galdente"/>
			</module>
		</product>
		<product id="dga_claytronics" ware="claytronics" owner="galdente" type="factory">
			<quotas>
				<quota galaxy="7"/>
			</quotas>
			<location class="galaxy" macro="xu_ep2_universe_macro" faction="[galdente]" relation="self" comparison="exact" matchextension="false" newzonechance="0">
				<security min="0.8"/>
			</location>
			<module>
				<select ware="claytronics" race="argon" faction="galdente"/>
			</module>
		</product>
		<product id="dga_dronecomponents" ware="dronecomponents" owner="galdente" type="factory">
			<quotas>
				<quota galaxy="2"/>
			</quotas>
			<location class="galaxy" macro="xu_ep2_universe_macro" faction="[galdente]" relation="self" comparison="exact" matchextension="false">
				<security min="0.6" max="0.8"/>
			</location>
			<module>
				<select ware="dronecomponents" race="argon" faction="galdente"/>
			</module>
		</product>
		<product id="dga_energycells" ware="energycells" owner="galdente" type="factory">
			<quotas>
				<quota galaxy="10"/>
			</quotas>
			<location class="galaxy" macro="xu_ep2_universe_macro" faction="[galdente]" relation="self" comparison="exact" matchextension="false">
				<sunlight min="1.4"/>
			</location>
			<module>
				<select ware="energycells" race="argon" faction="galdente"/>
			</module>
		</product>
		<product id="dga_engineparts" ware="engineparts" owner="galdente" type="factory">
			<quotas>
				<quota galaxy="2"/>
			</quotas>
			<location class="galaxy" macro="xu_ep2_universe_macro" faction="[galdente]" relation="self" comparison="exact" matchextension="false" newzonechance="0">
				<security min="0.8"/>
			</location>
			<module>
				<select ware="engineparts" race="argon" faction="galdente"/>
			</module>
		</product>
		<product id="dga_fieldcoils" ware="fieldcoils" owner="galdente" type="factory">
			<quotas>
				<quota galaxy="2"/>
			</quotas>
			<location class="galaxy" macro="xu_ep2_universe_macro" faction="[galdente]" relation="self" comparison="exact" matchextension="false">
				<security min="0.6" max="0.8"/>
			</location>
			<module>
				<select ware="fieldcoils" race="argon" faction="galdente"/>
			</module>
		</product>
		<product id="dga_foodrations" ware="foodrations" owner="galdente" type="factory">
			<quotas>
				<quota galaxy="11"/>
			</quotas>
			<location class="galaxy" macro="xu_ep2_universe_macro" faction="[galdente]" relation="self" comparison="exact" matchextension="false">
				<security min="0.4" max="0.6"/>
			</location>
			<module>
				<select ware="foodrations" race="argon" faction="galdente"/>
			</module>
		</product>
		<product id="dga_graphene" ware="graphene" owner="galdente" type="factory">
			<quotas>
				<quota galaxy="6"/>
			</quotas>
			<location class="galaxy" macro="xu_ep2_universe_macro" faction="[galdente]" relation="self" comparison="exact" matchextension="false">
				<region ware="methane" max="100000"/>
			</location>
			<module>
				<select ware="graphene" race="argon" faction="galdente"/>
			</module>
		</product>
		<product id="dga_hullparts" ware="hullparts" owner="galdente" type="factory">
			<quotas>
				<quota galaxy="20"/>
			</quotas>
			<location class="galaxy" macro="xu_ep2_universe_macro" faction="[galdente]" relation="self" comparison="exact" matchextension="false">
				<security min="0.6" max="0.8"/>
			</location>
			<module>
				<select ware="hullparts" race="argon" faction="galdente"/>
			</module>
		</product>
		<product id="dga_meat" ware="meat" owner="galdente" type="factory">
			<quotas>
				<quota galaxy="2"/>
			</quotas>
			<location class="galaxy" macro="xu_ep2_universe_macro" faction="[galdente]" relation="self" comparison="exact" matchextension="false">
				<security min="0.4" max="0.6"/>
			</location>
			<module>
				<select ware="meat" race="argon" faction="galdente"/>
			</module>
		</product>
		<product id="dga_medicalsupplies" ware="medicalsupplies" owner="galdente" type="factory">
			<quotas>
				<quota galaxy="22"/>
			</quotas>
			<location class="galaxy" macro="xu_ep2_universe_macro" faction="[galdente]" relation="self" comparison="exact" matchextension="false">
				<security min="0.4" max="0.6"/>
			</location>
			<module>
				<select ware="medicalsupplies" race="argon" faction="galdente"/>
			</module>
		</product>
		<product id="dga_microchips" ware="microchips" owner="galdente" type="factory">
			<quotas>
				<quota galaxy="8"/>
			</quotas>
			<location class="galaxy" macro="xu_ep2_universe_macro" faction="[galdente]" relation="self" comparison="exact" matchextension="false">
				<security min="0.6" max="0.8"/>
			</location>
			<module>
				<select ware="microchips" race="argon" faction="galdente"/>
			</module>
		</product>
		<product id="dga_missilecomponents" ware="missilecomponents" owner="galdente" type="factory">
			<quotas>
				<quota galaxy="2"/>
			</quotas>
			<location class="galaxy" macro="xu_ep2_universe_macro" faction="[galdente]" relation="self" comparison="exact" matchextension="false">
				<security min="0.4" max="0.6"/>
			</location>
			<module>
				<select ware="missilecomponents" race="argon" faction="galdente"/>
			</module>
		</product>
		<product id="dga_plasmaconductors" ware="plasmaconductors" owner="galdente" type="factory">
			<quotas>
				<quota galaxy="4"/>
			</quotas>
			<location class="galaxy" macro="xu_ep2_universe_macro" faction="[galdente]" relation="self" comparison="exact" matchextension="false">
				<security min="0.4" max="0.6"/>
			</location>
			<module>
				<select ware="plasmaconductors" race="argon" faction="galdente"/>
			</module>
		</product>
		<product id="dga_quantumtubes" ware="quantumtubes" owner="galdente" type="factory">
			<quotas>
				<quota galaxy="4"/>
			</quotas>
			<location class="galaxy" macro="xu_ep2_universe_macro" faction="[galdente]" relation="self" comparison="exact" matchextension="false">
				<security min="0.6" max="0.8"/>
			</location>
			<module>
				<select ware="quantumtubes" race="argon" faction="galdente"/>
			</module>
		</product>
		<product id="dga_refinedmetals" ware="refinedmetals" owner="galdente" type="factory">
			<quotas>
				<quota galaxy="6"/>
			</quotas>
			<location class="galaxy" macro="xu_ep2_universe_macro" faction="[galdente]" relation="self" comparison="exact" matchextension="false">
				<region ware="ore" max="100000"/>
			</location>
			<module>
				<select ware="refinedmetals" race="argon" faction="galdente"/>
			</module>
		</product>
		<product id="dga_scanningarrays" ware="scanningarrays" owner="galdente" type="factory">
			<quotas>
				<quota galaxy="2"/>
			</quotas>
			<location class="galaxy" macro="xu_ep2_universe_macro" faction="[galdente]" relation="self" comparison="exact" matchextension="false">
				<security min="0.6" max="0.8"/>
			</location>
			<module>
				<select ware="scanningarrays" race="argon" faction="galdente"/>
			</module>
		</product>
		<product id="dga_shieldcomponents" ware="shieldcomponents" owner="galdente" type="factory">
			<quotas>
				<quota galaxy="2"/>
			</quotas>
			<location class="galaxy" macro="xu_ep2_universe_macro" faction="[galdente]" relation="self" comparison="exact" matchextension="false">
				<security min="0.6" max="0.8"/>
			</location>
			<module>
				<select ware="shieldcomponents" race="argon" faction="galdente"/>
			</module>
		</product>
		<product id="dga_siliconwafers" ware="siliconwafers" owner="galdente" type="factory">
			<quotas>
				<quota galaxy="6"/>
			</quotas>
			<location class="galaxy" macro="xu_ep2_universe_macro" faction="[galdente]" relation="self" comparison="exact" matchextension="false">
				<region ware="silicon" max="100000"/>
			</location>
			<module>
				<select ware="siliconwafers" race="argon" faction="galdente"/>
			</module>
		</product>
		<product id="dga_smartchips" ware="smartchips" owner="galdente" type="factory">
			<quotas>
				<quota galaxy="8"/>
			</quotas>
			<location class="galaxy" macro="xu_ep2_universe_macro" faction="[galdente]" relation="self" comparison="exact" matchextension="false">
				<security min="0.6" max="0.8"/>
			</location>
			<module>
				<select ware="smartchips" race="argon" faction="galdente"/>
			</module>
		</product>
		<product id="dga_spices" ware="spices" owner="galdente" type="factory">
			<quotas>
				<quota galaxy="6"/>
			</quotas>
			<location class="galaxy" macro="xu_ep2_universe_macro" faction="[galdente]" relation="self" comparison="exact" matchextension="false">
				<security min="0.4" max="0.6"/>
			</location>
			<module>
				<select ware="spices" race="argon" faction="galdente"/>
			</module>
		</product>
		<product id="dga_superfluidcoolant" ware="superfluidcoolant" owner="galdente" type="factory">
			<quotas>
				<quota galaxy="2"/>
			</quotas>
			<location class="galaxy" macro="xu_ep2_universe_macro" faction="[galdente]" relation="self" comparison="exact" matchextension="false">
				<region ware="helium" max="100000"/>
			</location>
			<module>
				<select ware="superfluidcoolant" race="argon" faction="galdente"/>
			</module>
		</product>
		<product id="dga_turretcomponents" ware="turretcomponents" owner="galdente" type="factory">
			<quotas>
				<quota galaxy="2"/>
			</quotas>
			<location class="galaxy" macro="xu_ep2_universe_macro" faction="[galdente]" relation="self" comparison="exact" matchextension="false" newzonechance="0">
				<security min="0.8"/>
			</location>
			<module>
				<select ware="turretcomponents" race="argon" faction="galdente"/>
			</module>
		</product>
		<product id="dga_water" ware="water" owner="galdente" type="factory">
			<quotas>
				<quota galaxy="4"/>
			</quotas>
			<location class="galaxy" macro="xu_ep2_universe_macro" faction="[galdente]" relation="self" comparison="exact" matchextension="false">
				<region ware="ice" max="100000"/>
			</location>
			<module>
				<select ware="water" race="argon" faction="galdente"/>
			</module>
		</product>
		<product id="dga_weaponcomponents" ware="weaponcomponents" owner="galdente" type="factory">
			<quotas>
				<quota galaxy="4"/>
			</quotas>
			<location class="galaxy" macro="xu_ep2_universe_macro" faction="[galdente]" relation="self" comparison="exact" matchextension="false" newzonechance="0">
				<security min="0.8"/>
			</location>
			<module>
				<select ware="weaponcomponents" race="argon" faction="galdente"/>
			</module>
		</product>
		<product id="dga_wheat" ware="wheat" owner="galdente" type="factory">
			<quotas>
				<quota galaxy="4"/>
			</quotas>
			<location class="galaxy" macro="xu_ep2_universe_macro" faction="[galdente]" relation="self" comparison="exact" matchextension="false">
				<security min="0.4" max="0.6"/>
			</location>
			<module>
				<select ware="wheat" race="argon" faction="galdente"/>
			</module>
		</product>
		<product id="dga_da_adv_schematics" ware="da_adv_schematics" owner="galdente" type="factory">
			<quotas>
				<quota galaxy="4"/>
			</quotas>
			<location class="galaxy" macro="xu_ep2_universe_macro" faction="[galdente]" relation="self" comparison="exact" matchextension="false" newzonechance="0">
				<security min="0.8"/>
			</location>
			<module>
				<select ware="da_adv_schematics" race="argon" faction="galdente"/>
			</module>
		</product>
		<product id="dga_da_mil_schematics" ware="da_mil_schematics" owner="galdente" type="factory">
			<quotas>
				<quota galaxy="8"/>
			</quotas>
			<location class="galaxy" macro="xu_ep2_universe_macro" faction="[galdente]" relation="self" comparison="exact" matchextension="false">
				<security min="0.6" max="0.8"/>
			</location>
			<module>
				<select ware="da_mil_schematics" race="argon" faction="galdente"/>
			</module>
		</product>
		<product id="dga_da_laborunion_contracts" ware="da_laborunion_contracts" owner="galdente" type="factory">
			<quotas>
				<quota galaxy="16"/>
			</quotas>
			<location class="galaxy" macro="xu_ep2_universe_macro" faction="[galdente]" relation="self" comparison="exact" matchextension="false">
				<security min="0.4" max="0.6"/>
			</location>
			<module>
				<select ware="da_laborunion_contracts" race="argon" faction="galdente"/>
			</module>
		</product>
	</add>
	<!-- END PRODUCTS END PRODUCTS END PRODUCTS END PRODUCTS END PRODUCTS END PRODUCTS END PRODUCTS END PRODUCTS -->
</diff>